mail_agent/__init__.py
mail_agent/app.py
mail_agent/callback.py
mail_agent/cli.py
mail_agent/haraka.py
mail_agent/rabbitmq.py
mail_agent/smtp.py
mail_agent/utils.py
mail_agent-0.0.6.dist-info/METADATA
mail_agent-0.0.6.dist-info/WHEEL
mail_agent-0.0.6.dist-info/entry_points.txt
mail_agent-0.0.6.dist-info/top_level.txt
mail_agent-0.0.6.dist-info/RECORD
