Metadata-Version: 2.1
Name: mail-agent
Version: 0.0.6
Summary: Frappe Mail Agent
Home-page: https://github.com/frappe/mail_agent
Author: Frappe Technologies Pvt. Ltd.
Author-email: developers@frappe.io
Requires-Python: >=3.10
Requires-Dist: cffi==1.16.0
Requires-Dist: click==8.1.7
Requires-Dist: cryptography==42.0.8
Requires-Dist: distro==1.9.0
Requires-Dist: honcho==1.1.0
Requires-Dist: pika==1.3.2
Requires-Dist: pycparser==2.22
Requires-Dist: python-dotenv==1.0.1
